sciencebeam_trainer_delft/__init__.py
sciencebeam_trainer_delft/preprocess.py
sciencebeam_trainer_delft/embedding/__init__.py
sciencebeam_trainer_delft/embedding/__main__.py
sciencebeam_trainer_delft/embedding/cli.py
sciencebeam_trainer_delft/embedding/embedding.py
sciencebeam_trainer_delft/embedding/manager.py
sciencebeam_trainer_delft/grobid/__init__.py
sciencebeam_trainer_delft/grobid/lmdb_argv_workaround.py
sciencebeam_trainer_delft/grobid/sequenceLabelling/__init__.py
sciencebeam_trainer_delft/grobid/sequenceLabelling/reader.py
sciencebeam_trainer_delft/grobid/sequenceLabelling/wrapper.py
sciencebeam_trainer_delft/grobid/utilities/Embeddings.py
sciencebeam_trainer_delft/grobid/utilities/__init__.py
sciencebeam_trainer_delft/sequence_labelling/__init__.py
sciencebeam_trainer_delft/sequence_labelling/callbacks.py
sciencebeam_trainer_delft/sequence_labelling/config.py
sciencebeam_trainer_delft/sequence_labelling/data_generator.py
sciencebeam_trainer_delft/sequence_labelling/debug.py
sciencebeam_trainer_delft/sequence_labelling/evaluation.py
sciencebeam_trainer_delft/sequence_labelling/grobid_trainer.py
sciencebeam_trainer_delft/sequence_labelling/input_info.py
sciencebeam_trainer_delft/sequence_labelling/models.py
sciencebeam_trainer_delft/sequence_labelling/preprocess.py
sciencebeam_trainer_delft/sequence_labelling/reader.py
sciencebeam_trainer_delft/sequence_labelling/saving.py
sciencebeam_trainer_delft/sequence_labelling/tag_formatter.py
sciencebeam_trainer_delft/sequence_labelling/tagger.py
sciencebeam_trainer_delft/sequence_labelling/trainer.py
sciencebeam_trainer_delft/sequence_labelling/transfer_learning.py
sciencebeam_trainer_delft/sequence_labelling/typing.py
sciencebeam_trainer_delft/sequence_labelling/wrapper.py
sciencebeam_trainer_delft/sequence_labelling/dataset_transform/__init__.py
sciencebeam_trainer_delft/sequence_labelling/dataset_transform/unroll_transform.py
sciencebeam_trainer_delft/sequence_labelling/engines/__init__.py
sciencebeam_trainer_delft-0.0.34.dist-info/METADATA
sciencebeam_trainer_delft-0.0.34.dist-info/WHEEL
sciencebeam_trainer_delft-0.0.34.dist-info/top_level.txt
sciencebeam_trainer_delft-0.0.34.dist-info/RECORD
