Metadata-Version: 2.4
Name: sciencebeam-trainer-delft
Version: 0.0.34
Summary: ScienceBeam Trainer DeLFT
Requires-Python: >=3.9
Requires-Dist: jsonpickle>=1.4.1
Provides-Extra: tf
Requires-Dist: tensorflow==2.9.3; extra == "tf"
Provides-Extra: delft
Requires-Dist: blingfire==0.1.8; extra == "delft"
Requires-Dist: delft==0.3.4; extra == "delft"
